{
   "Feature" : {
      "from" : "Q9DC23",
      "model" : "SRHMM037293-1"
   },
   "Related" : "None",
   "AC" : "PIRSR037293-1",
   "Groups" : {
      "2" : [
         {
            "group" : "2",
            "label" : "DISULFID",
            "start" : 480,
            "hmmStart" : 481,
            "desc" : "Redox-active.",
            "hmmEnd" : 484,
            "end" : 483,
            "condition" : "C-x(2)-C"
         }
      ],
      "1" : [
         {
            "end" : 161,
            "hmmEnd" : 162,
            "desc" : "Redox-active.",
            "condition" : "C-x(2)-C",
            "group" : "1",
            "hmmStart" : 159,
            "label" : "DISULFID",
            "start" : 158
         }
      ],
      "3" : [
         {
            "group" : "3",
            "label" : "DISULFID",
            "start" : 588,
            "hmmStart" : 589,
            "desc" : "Redox-active.",
            "hmmEnd" : 592,
            "end" : 591,
            "condition" : "C-x(2)-C"
         }
      ],
      "4" : [
         {
            "condition" : "C-x(2)-C",
            "desc" : "Redox-active.",
            "hmmEnd" : 704,
            "end" : 703,
            "hmmStart" : 701,
            "start" : 700,
            "label" : "DISULFID",
            "group" : "4"
         }
      ]
   },
   "Scope" : [
      "Eukaryota"
   ],
   "TR" : "PIRSF; PIRSF037293; -; 1",
   "DC" : "Domain",
   "Size" : "unlimited"
}
